koloro/__init__.py
koloro/__main__.py
koloro/py.typed
koloro-0.1.4.dist-info/LICENSE
koloro-0.1.4.dist-info/METADATA
koloro-0.1.4.dist-info/WHEEL
koloro-0.1.4.dist-info/top_level.txt
koloro-0.1.4.dist-info/RECORD
