Metadata-Version: 2.1
Name: koloro
Version: 0.1.4
Summary: Koloro - colorful terminal text in Python
Home-page: https://github.com/ydcjeff/koloro
Author: Jeff Yang
Author-email: ydcjeff@gmail.com
License: MIT
Download-URL: https://pypi.org/project/koloro/#files
Project-URL: Documentation, https://github.com/ydcjeff/koloro/#readme
Project-URL: Source Code, https://github.com/ydcjeff/koloro
Project-URL: Bug Tracker, https://github.com/ydcjeff/koloro/issues
Project-URL: Changelog, https://github.com/ydcjeff/koloro/blob/main/CHANGELOG.md
Keywords: python,cli,terminal,styling,ansi,ansi-colors,colorful
Platform: UNKNOWN
Classifier: Development Status :: 4 - Beta
Classifier: Environment :: Console
Classifier: Intended Audience :: Developers
Classifier: Intended Audience :: Science/Research
Classifier: License :: OSI Approved :: MIT License
Classifier: Programming Language :: Python :: 3
Classifier: Topic :: Software Development
Classifier: Topic :: Software Development :: Libraries
Classifier: Topic :: Software Development :: Libraries :: Python Modules
Classifier: Topic :: Utilities
Classifier: Typing :: Typed
Requires-Python: >=3.6
License-File: LICENSE
Provides-Extra: dev
Requires-Dist: pytest ; extra == 'dev'
Requires-Dist: pytest-cov ; extra == 'dev'
Requires-Dist: black (==21.6b0) ; extra == 'dev'
Requires-Dist: mypy ; extra == 'dev'
Requires-Dist: isort ; extra == 'dev'
Requires-Dist: flake8 ; extra == 'dev'
Provides-Extra: tests
Requires-Dist: pytest ; extra == 'tests'
Requires-Dist: pytest-cov ; extra == 'tests'
Requires-Dist: black (==21.6b0) ; extra == 'tests'
Requires-Dist: mypy ; extra == 'tests'
Requires-Dist: isort ; extra == 'tests'
Requires-Dist: flake8 ; extra == 'tests'
